{
	"nodes": [
		{
			"width": 170,
			"height": 124,
			"id": "Agama-log-Node-c19f4a59-7153-432b-b971-713922e1f6f9",
			"position": {
				"x": 880,
				"y": 30
			},
			"type": "log",
			"data": {
				"id": "Agama-log-Node-c19f4a59-7153-432b-b971-713922e1f6f9",
				"type": "Agama-log-Node",
				"parentId": "Agama-repeat-Node-1b9818a0-125b-4c4e-a880-d51bb3799694",
				"whenCondition": "",
				"inRepeatBlock": false,
				"position": {
					"x": 880,
					"y": 30
				},
				"agamaData": {
					"id": "Agama-log-Node-c19f4a59-7153-432b-b971-713922e1f6f9",
					"parentId": "Agama-repeat-Node-1b9818a0-125b-4c4e-a880-d51bb3799694",
					"type": "Agama-log-Node",
					"displayName": "OTP validation failed!",
					"hasComment": true,
					"comment": " Maximum attempts reached. OTP validation failed!",
					"whenCondition": "",
					"inRepeatBlock": false,
					"logMessage": "\"Maximum attempts reached. OTP validation failed!\"",
					"logLevel": "error",
					"nodeIcon": "octicon:log-16"
				}
			},
			"selected": true,
			"dragging": false,
			"positionAbsolute": {
				"x": 880,
				"y": 30
			}
		},
		{
			"width": 170,
			"height": 124,
			"id": "Agama-assignment-Node-75f433ab-c00d-4996-ab1f-3b2e360babfe",
			"position": {
				"x": 2009.8685916587601,
				"y": 257.6055156549651
			},
			"type": "assignment",
			"data": {
				"id": "Agama-assignment-Node-75f433ab-c00d-4996-ab1f-3b2e360babfe",
				"type": "Agama-assignment-Node",
				"parentId": "Agama-log-Node-8a2e2be3-e151-4aa1-85c3-50ecbdb7af37",
				"whenCondition": "",
				"inRepeatBlock": true,
				"position": {
					"x": 2009.8685916587601,
					"y": 257.6055156549651
				},
				"agamaData": {
					"id": "Agama-assignment-Node-75f433ab-c00d-4996-ab1f-3b2e360babfe",
					"parentId": "Agama-log-Node-8a2e2be3-e151-4aa1-85c3-50ecbdb7af37",
					"type": "Agama-assignment-Node",
					"displayName": "Error feedback",
					"hasComment": true,
					"comment": "Provide feedback about the error message to user",
					"whenCondition": "",
					"inRepeatBlock": true,
					"assignments": [
						{
							"variableTypeCheck": true,
							"assignmentExpression": "The provided code is not valid",
							"assignedVariableName": "otpUiFeedback.errorMessage"
						}
					],
					"nodeIcon": "material-symbols:equal"
				},
				"skake": false
			},
			"selected": false,
			"positionAbsolute": {
				"x": 2009.8685916587601,
				"y": 257.6055156549651
			},
			"dragging": false
		},
		{
			"width": 170,
			"height": 124,
			"id": "Agama-log-Node-8a2e2be3-e151-4aa1-85c3-50ecbdb7af37",
			"position": {
				"x": 1811.2633353251103,
				"y": 259.0002593213154
			},
			"type": "log",
			"data": {
				"id": "Agama-log-Node-8a2e2be3-e151-4aa1-85c3-50ecbdb7af37",
				"type": "Agama-log-Node",
				"parentId": "Agama-when-Node-6baa7e18-260e-4cb3-a4d8-2f2a71b0647d",
				"whenCondition": "WhenFalse",
				"inRepeatBlock": true,
				"position": {
					"x": 1811.2633353251103,
					"y": 259.0002593213154
				},
				"agamaData": {
					"id": "Agama-log-Node-8a2e2be3-e151-4aa1-85c3-50ecbdb7af37",
					"parentId": "Agama-when-Node-6baa7e18-260e-4cb3-a4d8-2f2a71b0647d",
					"type": "Agama-log-Node",
					"displayName": "Log Invalid attempt",
					"hasComment": true,
					"comment": "",
					"whenCondition": "WhenFalse",
					"inRepeatBlock": true,
					"logMessage": "\"Invalid code provided\"",
					"logLevel": "error",
					"nodeIcon": "octicon:log-16"
				},
				"skake": false
			},
			"selected": false,
			"dragging": false,
			"positionAbsolute": {
				"x": 1811.2633353251103,
				"y": 259.0002593213154
			}
		},
		{
			"width": 170,
			"height": 124,
			"id": "finish-3096f447-2fda-4095-beae-e9cd8a58d531",
			"position": {
				"x": 1674.2633353251103,
				"y": 543.0002593213154
			},
			"type": "finish",
			"data": {
				"id": "finish-3096f447-2fda-4095-beae-e9cd8a58d531",
				"type": "Agama-finish-Flow",
				"parentId": "Agama-when-Node-6baa7e18-260e-4cb3-a4d8-2f2a71b0647d",
				"whenCondition": "WhenTrue",
				"inRepeatBlock": true,
				"handles": [
					"Agama-when-Node-6baa7e18-260e-4cb3-a4d8-2f2a71b0647d.FAILURE",
					"Agama-when-Node-6baa7e18-260e-4cb3-a4d8-2f2a71b0647d.SUCCESS"
				],
				"position": {
					"x": 1674.2633353251103,
					"y": 543.0002593213154
				},
				"agamaData": {
					"id": "finish-3096f447-2fda-4095-beae-e9cd8a58d531",
					"parentId": "Agama-when-Node-6baa7e18-260e-4cb3-a4d8-2f2a71b0647d",
					"type": "Agama-finish-Flow",
					"hasSuccess": false,
					"hasFailure": false,
					"hasComment": true,
					"comment": "",
					"flowfilename": "",
					"returnVariable": "otpValidationResult",
					"finishMode": "withVariable",
					"nodeIcon": "material-symbols:line-end-square-rounded",
					"displayName": "OTP Check Succeed"
				},
				"skake": false
			},
			"selected": false,
			"dragging": false,
			"positionAbsolute": {
				"x": 1674.2633353251103,
				"y": 543.0002593213154
			}
		},
		{
			"width": 210,
			"height": 140,
			"id": "Agama-when-Node-6baa7e18-260e-4cb3-a4d8-2f2a71b0647d",
			"position": {
				"x": 1561.2633353251103,
				"y": 313.0002593213154
			},
			"parentId": "Agama-log-Node-4c2bee7c-a538-4734-9a1c-797e2c71ca1e",
			"type": "when",
			"data": {
				"id": "Agama-when-Node-6baa7e18-260e-4cb3-a4d8-2f2a71b0647d",
				"type": "Agama-when-Node",
				"parentId": "Agama-log-Node-4c2bee7c-a538-4734-9a1c-797e2c71ca1e",
				"whenCondition": "",
				"inRepeatBlock": true,
				"position": {
					"x": 1561.2633353251103,
					"y": 313.0002593213154
				},
				"agamaData": {
					"id": "Agama-when-Node-6baa7e18-260e-4cb3-a4d8-2f2a71b0647d",
					"parentId": "Agama-log-Node-4c2bee7c-a538-4734-9a1c-797e2c71ca1e",
					"type": "Agama-when-Node",
					"conditions": [
						{
							"variable": "otpValidationResult",
							"operator": "is",
							"dataValue": "true",
							"combinator": "none"
						}
					],
					"comment": "If otp validation was successful",
					"hasComment": true,
					"inRepeatBlock": true,
					"hasSuccess": true,
					"hasFailure": true
				},
				"handles": [
					"Agama-when-Node-6baa7e18-260e-4cb3-a4d8-2f2a71b0647d.FAILURE",
					"Agama-when-Node-6baa7e18-260e-4cb3-a4d8-2f2a71b0647d.SUCCESS"
				],
				"skake": false
			},
			"selected": false,
			"positionAbsolute": {
				"x": 1561.2633353251103,
				"y": 313.0002593213154
			},
			"dragging": false
		},
		{
			"width": 170,
			"height": 124,
			"id": "Agama-log-Node-4c2bee7c-a538-4734-9a1c-797e2c71ca1e",
			"position": {
				"x": 1325,
				"y": 258.60525633364966
			},
			"type": "log",
			"data": {
				"id": "Agama-log-Node-4c2bee7c-a538-4734-9a1c-797e2c71ca1e",
				"type": "Agama-log-Node",
				"parentId": "Agama-call-Node-80507823-c71b-4734-8d2e-a8db5f3fd7a4",
				"whenCondition": "",
				"inRepeatBlock": true,
				"position": {
					"x": 1325,
					"y": 258.60525633364966
				},
				"agamaData": {
					"id": "Agama-log-Node-4c2bee7c-a538-4734-9a1c-797e2c71ca1e",
					"parentId": "Agama-call-Node-80507823-c71b-4734-8d2e-a8db5f3fd7a4",
					"type": "Agama-log-Node",
					"displayName": "Log validation result",
					"hasComment": true,
					"comment": "",
					"whenCondition": "",
					"inRepeatBlock": true,
					"logMessage": "\"OTP validation result is:\" otpValidationResult otpValidationException",
					"logLevel": "info",
					"nodeIcon": "octicon:log-16"
				},
				"skake": false
			},
			"selected": false,
			"dragging": false,
			"positionAbsolute": {
				"x": 1325,
				"y": 258.60525633364966
			}
		},
		{
			"width": 170,
			"height": 124,
			"id": "Agama-call-Node-80507823-c71b-4734-8d2e-a8db5f3fd7a4",
			"position": {
				"x": 1125,
				"y": 258.60525633364966
			},
			"type": "call",
			"data": {
				"id": "Agama-call-Node-80507823-c71b-4734-8d2e-a8db5f3fd7a4",
				"type": "Agama-call-Node",
				"parentId": "Agama-log-Node-0d1ad8ff-eff4-4218-af6a-80b3a18e9da3",
				"whenCondition": "",
				"inRepeatBlock": true,
				"position": {
					"x": 1125,
					"y": 258.60525633364966
				},
				"agamaData": {
					"id": "Agama-call-Node-80507823-c71b-4734-8d2e-a8db5f3fd7a4",
					"parentId": "Agama-log-Node-0d1ad8ff-eff4-4218-af6a-80b3a18e9da3",
					"type": "Agama-call-Node",
					"displayName": "Validate OTP Code",
					"hasComment": true,
					"comment": "",
					"javaClassName": "",
					"javaMethodName": "validateOTPCode",
					"javaVariableName": "otpService",
					"exceptionVariableField": "otpValidationException",
					"callType": "Call method on instance",
					"whenCondition": "",
					"inRepeatBlock": true,
					"arguments": [
						"username",
						"otpCreds.code"
					],
					"nodeIcon": "material-symbols:code",
					"asssignedVariableName": "otpValidationResult"
				},
				"skake": false
			},
			"selected": false,
			"dragging": false,
			"positionAbsolute": {
				"x": 1125,
				"y": 258.60525633364966
			}
		},
		{
			"width": 170,
			"height": 124,
			"id": "Agama-log-Node-0d1ad8ff-eff4-4218-af6a-80b3a18e9da3",
			"position": {
				"x": 925,
				"y": 258.60525633364966
			},
			"type": "log",
			"data": {
				"id": "Agama-log-Node-0d1ad8ff-eff4-4218-af6a-80b3a18e9da3",
				"type": "Agama-log-Node",
				"parentId": "Agama-rrf-Node-3aeb6cd1-c67d-43b9-81c1-44348e2fc0a8",
				"whenCondition": "",
				"inRepeatBlock": true,
				"position": {
					"x": 925,
					"y": 258.60525633364966
				},
				"agamaData": {
					"id": "Agama-log-Node-0d1ad8ff-eff4-4218-af6a-80b3a18e9da3",
					"parentId": "Agama-rrf-Node-3aeb6cd1-c67d-43b9-81c1-44348e2fc0a8",
					"type": "Agama-log-Node",
					"displayName": "Log user provided code",
					"hasComment": true,
					"comment": "",
					"whenCondition": "",
					"inRepeatBlock": true,
					"logMessage": "\"OTP Code provided by the user is : \" otpCreds.code otpCount",
					"logLevel": "info",
					"nodeIcon": "octicon:log-16"
				},
				"skake": false
			},
			"selected": false,
			"dragging": false,
			"positionAbsolute": {
				"x": 925,
				"y": 258.60525633364966
			}
		},
		{
			"width": 170,
			"height": 124,
			"id": "Agama-rrf-Node-3aeb6cd1-c67d-43b9-81c1-44348e2fc0a8",
			"position": {
				"x": 725,
				"y": 260
			},
			"type": "rrf",
			"data": {
				"id": "Agama-rrf-Node-3aeb6cd1-c67d-43b9-81c1-44348e2fc0a8",
				"type": "Agama-rrf-Node",
				"parentId": "Agama-repeat-Node-1b9818a0-125b-4c4e-a880-d51bb3799694",
				"whenCondition": "",
				"inRepeatBlock": true,
				"position": {
					"x": 725,
					"y": 260
				},
				"agamaData": {
					"id": "Agama-rrf-Node-3aeb6cd1-c67d-43b9-81c1-44348e2fc0a8",
					"parentId": "Agama-repeat-Node-1b9818a0-125b-4c4e-a880-d51bb3799694",
					"type": "Agama-rrf-Node",
					"displayName": "Collect User OTP Code",
					"hasComment": true,
					"comment": "",
					"whenCondition": "",
					"inRepeatBlock": true,
					"assignments": [],
					"nodeIcon": "ph:globe-simple",
					"templatePath": "otp.ftlh",
					"asssignedVariableName": "otpCreds",
					"arguments": "otpUiFeedback"
				},
				"skake": false
			},
			"selected": false,
			"dragging": false,
			"positionAbsolute": {
				"x": 725,
				"y": 260
			}
		},
		{
			"width": 170,
			"height": 124,
			"id": "Agama-repeat-Node-1b9818a0-125b-4c4e-a880-d51bb3799694",
			"position": {
				"x": 630,
				"y": 30
			},
			"type": "repeat",
			"data": {
				"id": "Agama-repeat-Node-1b9818a0-125b-4c4e-a880-d51bb3799694",
				"type": "Agama-repeat-Node",
				"parentId": "Agama-assignment-Node-b82318f3-0f2d-47fa-8e4a-f9fa1cbdb43d",
				"whenCondition": "",
				"inRepeatBlock": false,
				"handles": [
					"Agama-repeat-Node-1b9818a0-125b-4c4e-a880-d51bb3799694.InFlow",
					"Agama-repeat-Node-1b9818a0-125b-4c4e-a880-d51bb3799694.InRepeatBlock"
				],
				"position": {
					"x": 630,
					"y": 30
				},
				"agamaData": {
					"id": "Agama-repeat-Node-1b9818a0-125b-4c4e-a880-d51bb3799694",
					"parentId": "Agama-assignment-Node-b82318f3-0f2d-47fa-8e4a-f9fa1cbdb43d",
					"type": "Agama-repeat-Node",
					"nodeIcon": "material-symbols:event-repeat-outline-rounded",
					"maxIteration": "3",
					"maxIterationVariableName": "otpCount",
					"displayName": "OPT Validation Loop",
					"hasComment": true,
					"hasNoRepeat": true
				},
				"skake": false
			},
			"selected": false,
			"dragging": false,
			"positionAbsolute": {
				"x": 630,
				"y": 30
			}
		},
		{
			"width": 170,
			"height": 124,
			"id": "Agama-assignment-Node-b82318f3-0f2d-47fa-8e4a-f9fa1cbdb43d",
			"position": {
				"x": 430,
				"y": 30
			},
			"type": "assignment",
			"data": {
				"id": "Agama-assignment-Node-b82318f3-0f2d-47fa-8e4a-f9fa1cbdb43d",
				"type": "Agama-assignment-Node",
				"parentId": "Agama-log-Node-c1e3cf40-4373-43bc-a945-1d31205b550b",
				"whenCondition": "",
				"inRepeatBlock": false,
				"position": {
					"x": 430,
					"y": 30
				},
				"agamaData": {
					"id": "Agama-assignment-Node-b82318f3-0f2d-47fa-8e4a-f9fa1cbdb43d",
					"parentId": "Agama-log-Node-c1e3cf40-4373-43bc-a945-1d31205b550b",
					"type": "Agama-assignment-Node",
					"displayName": "Declare feedback Variable",
					"hasComment": true,
					"comment": "Declare a variable for Ui feedback messages",
					"whenCondition": "",
					"inRepeatBlock": false,
					"assignments": [
						{
							"variableTypeCheck": false,
							"assignmentExpression": "{}",
							"assignedVariableName": "otpUiFeedback"
						},
						{
							"variableTypeCheck": false,
							"assignmentExpression": "maskedPhone",
							"assignedVariableName": "otpUiFeedback.maskedPhone"
						}
					],
					"nodeIcon": "material-symbols:equal"
				},
				"skake": false
			},
			"selected": false,
			"dragging": false,
			"positionAbsolute": {
				"x": 430,
				"y": 30
			}
		},
		{
			"width": 170,
			"height": 124,
			"id": "Agama-log-Node-c1e3cf40-4373-43bc-a945-1d31205b550b",
			"position": {
				"x": 230,
				"y": 30
			},
			"type": "log",
			"data": {
				"id": "Agama-log-Node-c1e3cf40-4373-43bc-a945-1d31205b550b",
				"type": "Agama-log-Node",
				"parentId": "Agama-start-Flow-064f782c-6ade-40b5-a888-8c555752ab15",
				"whenCondition": "",
				"inRepeatBlock": false,
				"position": {
					"x": 230,
					"y": 30
				},
				"agamaData": {
					"id": "Agama-log-Node-c1e3cf40-4373-43bc-a945-1d31205b550b",
					"parentId": "Agama-start-Flow-064f782c-6ade-40b5-a888-8c555752ab15",
					"type": "Agama-log-Node",
					"displayName": "Log flow imputs",
					"hasComment": true,
					"comment": "",
					"whenCondition": "",
					"inRepeatBlock": false,
					"logMessage": "\"Information received by the called:\" username maskedPhone",
					"logLevel": "info",
					"nodeIcon": "octicon:log-16"
				},
				"skake": false
			},
			"selected": false,
			"dragging": false,
			"positionAbsolute": {
				"x": 230,
				"y": 30
			}
		},
		{
			"width": 170,
			"height": 124,
			"id": "Agama-start-Flow-064f782c-6ade-40b5-a888-8c555752ab15",
			"type": "start",
			"sourcePosition": "right",
			"data": {
				"id": "Agama-start-Flow-064f782c-6ade-40b5-a888-8c555752ab15",
				"type": "Agama-start-Flow",
				"position": {
					"x": 30,
					"y": 30
				},
				"inRepeatBlock": false,
				"agamaData": {
					"id": "Agama-start-Flow-064f782c-6ade-40b5-a888-8c555752ab15",
					"type": "Agama-start-Flow",
					"displayName": "SMS OTP Flow",
					"hasComment": true,
					"comment": "",
					"isTopLevelFlow": true,
					"basepath": "",
					"configParams": "{}",
					"nodeIcon": "material-symbols:line-start-square",
					"timeout": "",
					"inputs": "otpService username maskedPhone",
					"configs": "",
					"flowname": "org.gluu.agama.sms.otp"
				},
				"skake": false
			},
			"position": {
				"x": 30,
				"y": 30
			},
			"selected": false,
			"dragging": false,
			"positionAbsolute": {
				"x": 30,
				"y": 30
			}
		}
	],
	"edges": [
		{
			"id": "Agama-start-Flow-064f782c-6ade-40b5-a888-8c555752ab15-Agama-log-Node-c1e3cf40-4373-43bc-a945-1d31205b550b-269825f3-b232-48a1-8f0e-228bfc318745",
			"type": "straight",
			"source": "Agama-start-Flow-064f782c-6ade-40b5-a888-8c555752ab15",
			"target": "Agama-log-Node-c1e3cf40-4373-43bc-a945-1d31205b550b",
			"label": "",
			"labelBgPadding": [
				8,
				4
			],
			"labelBgBorderRadius": 4,
			"labelBgStyle": {
				"fill": "#FFCC00",
				"color": "#fff",
				"fillOpacity": 0.7
			}
		},
		{
			"id": "Agama-log-Node-c1e3cf40-4373-43bc-a945-1d31205b550b-Agama-assignment-Node-b82318f3-0f2d-47fa-8e4a-f9fa1cbdb43d-3fdda273-9a49-4a4b-9732-2cef05ce8f58",
			"type": "straight",
			"source": "Agama-log-Node-c1e3cf40-4373-43bc-a945-1d31205b550b",
			"target": "Agama-assignment-Node-b82318f3-0f2d-47fa-8e4a-f9fa1cbdb43d",
			"label": "",
			"labelBgPadding": [
				8,
				4
			],
			"labelBgBorderRadius": 4,
			"labelBgStyle": {
				"fill": "#FFCC00",
				"color": "#fff",
				"fillOpacity": 0.7
			}
		},
		{
			"id": "Agama-assignment-Node-b82318f3-0f2d-47fa-8e4a-f9fa1cbdb43d-Agama-repeat-Node-1b9818a0-125b-4c4e-a880-d51bb3799694-42d47b08-5a65-4db7-9029-6ed364b0a754",
			"type": "straight",
			"source": "Agama-assignment-Node-b82318f3-0f2d-47fa-8e4a-f9fa1cbdb43d",
			"target": "Agama-repeat-Node-1b9818a0-125b-4c4e-a880-d51bb3799694",
			"label": "",
			"labelBgPadding": [
				8,
				4
			],
			"labelBgBorderRadius": 4,
			"labelBgStyle": {
				"fill": "#FFCC00",
				"color": "#fff",
				"fillOpacity": 0.7
			}
		},
		{
			"id": "Agama-repeat-Node-1b9818a0-125b-4c4e-a880-d51bb3799694-Agama-rrf-Node-3aeb6cd1-c67d-43b9-81c1-44348e2fc0a8-07c05639-21c8-46a2-b543-c76653b6524c",
			"type": "straight",
			"source": "Agama-repeat-Node-1b9818a0-125b-4c4e-a880-d51bb3799694",
			"target": "Agama-rrf-Node-3aeb6cd1-c67d-43b9-81c1-44348e2fc0a8",
			"label": "In Block",
			"labelBgPadding": [
				8,
				4
			],
			"labelBgBorderRadius": 4,
			"labelBgStyle": {
				"fill": "#FFCC00",
				"color": "#fff",
				"fillOpacity": 0.7
			},
			"sourceHandle": "Agama-repeat-Node-1b9818a0-125b-4c4e-a880-d51bb3799694.InRepeatBlock"
		},
		{
			"id": "Agama-rrf-Node-3aeb6cd1-c67d-43b9-81c1-44348e2fc0a8-Agama-log-Node-0d1ad8ff-eff4-4218-af6a-80b3a18e9da3-0f6ab2e0-9436-468b-9c4b-6d28bf3f6b69",
			"type": "straight",
			"source": "Agama-rrf-Node-3aeb6cd1-c67d-43b9-81c1-44348e2fc0a8",
			"target": "Agama-log-Node-0d1ad8ff-eff4-4218-af6a-80b3a18e9da3",
			"label": "",
			"labelBgPadding": [
				8,
				4
			],
			"labelBgBorderRadius": 4,
			"labelBgStyle": {
				"fill": "#FFCC00",
				"color": "#fff",
				"fillOpacity": 0.7
			}
		},
		{
			"id": "Agama-log-Node-0d1ad8ff-eff4-4218-af6a-80b3a18e9da3-Agama-call-Node-80507823-c71b-4734-8d2e-a8db5f3fd7a4-c69b6a51-f09e-4d25-b64d-f14639f9add2",
			"type": "straight",
			"source": "Agama-log-Node-0d1ad8ff-eff4-4218-af6a-80b3a18e9da3",
			"target": "Agama-call-Node-80507823-c71b-4734-8d2e-a8db5f3fd7a4",
			"label": "",
			"labelBgPadding": [
				8,
				4
			],
			"labelBgBorderRadius": 4,
			"labelBgStyle": {
				"fill": "#FFCC00",
				"color": "#fff",
				"fillOpacity": 0.7
			}
		},
		{
			"id": "Agama-call-Node-80507823-c71b-4734-8d2e-a8db5f3fd7a4-Agama-when-Node-ab2dcea2-6435-4568-a97d-5c2117848231-ea13e0d3-c714-4e34-990d-43fcffc123fd",
			"type": "straight",
			"source": "Agama-call-Node-80507823-c71b-4734-8d2e-a8db5f3fd7a4",
			"target": "Agama-when-Node-ab2dcea2-6435-4568-a97d-5c2117848231",
			"label": "",
			"labelBgPadding": [
				8,
				4
			],
			"labelBgBorderRadius": 4,
			"labelBgStyle": {
				"fill": "#FFCC00",
				"color": "#fff",
				"fillOpacity": 0.7
			}
		},
		{
			"id": "Agama-call-Node-80507823-c71b-4734-8d2e-a8db5f3fd7a4-Agama-log-Node-4c2bee7c-a538-4734-9a1c-797e2c71ca1e-96fed987-2737-44eb-b921-f744783f4e52",
			"type": "straight",
			"source": "Agama-call-Node-80507823-c71b-4734-8d2e-a8db5f3fd7a4",
			"target": "Agama-log-Node-4c2bee7c-a538-4734-9a1c-797e2c71ca1e",
			"label": "",
			"labelBgPadding": [
				8,
				4
			],
			"labelBgBorderRadius": 4,
			"labelBgStyle": {
				"fill": "#FFCC00",
				"color": "#fff",
				"fillOpacity": 0.7
			}
		},
		{
			"id": "Agama-log-Node-4c2bee7c-a538-4734-9a1c-797e2c71ca1e-Agama-when-Node-6baa7e18-260e-4cb3-a4d8-2f2a71b0647d-de06ea4b-33eb-42f2-ac4e-0efb3b0df961",
			"type": "straight",
			"source": "Agama-log-Node-4c2bee7c-a538-4734-9a1c-797e2c71ca1e",
			"target": "Agama-when-Node-6baa7e18-260e-4cb3-a4d8-2f2a71b0647d",
			"label": "",
			"labelBgPadding": [
				8,
				4
			],
			"labelBgBorderRadius": 4,
			"labelBgStyle": {
				"fill": "#FFCC00",
				"color": "#fff",
				"fillOpacity": 0.7
			}
		},
		{
			"id": "Agama-when-Node-6baa7e18-260e-4cb3-a4d8-2f2a71b0647d-finish-3096f447-2fda-4095-beae-e9cd8a58d531-641ed2bb-2484-408f-8a9b-1bbf1acf23ae",
			"type": "straight",
			"source": "Agama-when-Node-6baa7e18-260e-4cb3-a4d8-2f2a71b0647d",
			"target": "finish-3096f447-2fda-4095-beae-e9cd8a58d531",
			"label": "Condition met",
			"labelBgPadding": [
				8,
				4
			],
			"labelBgBorderRadius": 4,
			"labelBgStyle": {
				"fill": "#FFCC00",
				"color": "#fff",
				"fillOpacity": 0.7
			},
			"sourceHandle": "Agama-when-Node-6baa7e18-260e-4cb3-a4d8-2f2a71b0647d.SUCCESS"
		},
		{
			"id": "Agama-when-Node-6baa7e18-260e-4cb3-a4d8-2f2a71b0647d-Agama-log-Node-8a2e2be3-e151-4aa1-85c3-50ecbdb7af37-1b90cdde-9adf-4715-b91a-21f132d5db05",
			"type": "straight",
			"source": "Agama-when-Node-6baa7e18-260e-4cb3-a4d8-2f2a71b0647d",
			"target": "Agama-log-Node-8a2e2be3-e151-4aa1-85c3-50ecbdb7af37",
			"label": "",
			"labelBgPadding": [
				8,
				4
			],
			"labelBgBorderRadius": 4,
			"labelBgStyle": {
				"fill": "#FFCC00",
				"color": "#fff",
				"fillOpacity": 0.7
			},
			"sourceHandle": "Agama-when-Node-6baa7e18-260e-4cb3-a4d8-2f2a71b0647d.FAILURE"
		},
		{
			"id": "Agama-log-Node-8a2e2be3-e151-4aa1-85c3-50ecbdb7af37-Agama-assignment-Node-75f433ab-c00d-4996-ab1f-3b2e360babfe-1fc56e2c-63d6-4fff-9f0c-b2e4bfcebdbd",
			"type": "straight",
			"source": "Agama-log-Node-8a2e2be3-e151-4aa1-85c3-50ecbdb7af37",
			"target": "Agama-assignment-Node-75f433ab-c00d-4996-ab1f-3b2e360babfe",
			"label": "",
			"labelBgPadding": [
				8,
				4
			],
			"labelBgBorderRadius": 4,
			"labelBgStyle": {
				"fill": "#FFCC00",
				"color": "#fff",
				"fillOpacity": 0.7
			}
		},
		{
			"id": "Agama-repeat-Node-1b9818a0-125b-4c4e-a880-d51bb3799694-Agama-log-Node-c19f4a59-7153-432b-b971-713922e1f6f9-a9dcd141-ec78-485f-9196-4801b1b19116",
			"type": "straight",
			"source": "Agama-repeat-Node-1b9818a0-125b-4c4e-a880-d51bb3799694",
			"target": "Agama-log-Node-c19f4a59-7153-432b-b971-713922e1f6f9",
			"label": "Not In Block",
			"labelBgPadding": [
				8,
				4
			],
			"labelBgBorderRadius": 4,
			"labelBgStyle": {
				"fill": "#FFCC00",
				"color": "#fff",
				"fillOpacity": 0.7
			},
			"sourceHandle": "Agama-repeat-Node-1b9818a0-125b-4c4e-a880-d51bb3799694.InFlow"
		}
	],
	"viewport": {
		"x": 81.25796672286927,
		"y": 183.9820862698474,
		"zoom": 0.7169776240079139
	}
}